observamax/__init__.py
observamax/client.py
observamax/exceptions.py
observamax/models.py
observamax-1.0.0.dist-info/METADATA
observamax-1.0.0.dist-info/WHEEL
observamax-1.0.0.dist-info/RECORD
