Metadata-Version: 2.4
Name: observamax
Version: 1.0.0
Summary: Official Python SDK for ObservaMax API
Project-URL: Homepage, https://observamax.com
Project-URL: Documentation, https://observamax.com/developers
Project-URL: Repository, https://github.com/observamax/sdk-python
Author-email: ObservaMax <support@observamax.com>
License-Expression: MIT
Keywords: api,monitoring,observamax,sdk,uptime
Classifier: Development Status :: 5 - Production/Stable
Classifier: Intended Audience :: Developers
Classifier: License :: OSI Approved :: MIT License
Classifier: Programming Language :: Python :: 3
Classifier: Programming Language :: Python :: 3.8
Classifier: Programming Language :: Python :: 3.9
Classifier: Programming Language :: Python :: 3.10
Classifier: Programming Language :: Python :: 3.11
Classifier: Programming Language :: Python :: 3.12
Classifier: Topic :: Internet :: WWW/HTTP
Classifier: Topic :: System :: Monitoring
Requires-Python: >=3.8
Requires-Dist: httpx>=0.25.0
Requires-Dist: pydantic>=2.0.0
